termos/__init__.py
termos/auth.py
termos/bash_cmd_exe.py
termos/exceptions.py
termos/file_editor.py
termos/main.py
termos-0.1.9.dist-info/LICENSE
termos-0.1.9.dist-info/METADATA
termos-0.1.9.dist-info/WHEEL
termos-0.1.9.dist-info/entry_points.txt
termos-0.1.9.dist-info/top_level.txt
termos-0.1.9.dist-info/RECORD
