Metadata-Version: 2.1
Name: termos
Version: 0.1.9
Summary: A CLI tool for executing tasks using OpenAI's assistant
Home-page: https://github.com/yourusername/termos
Author: Your Name
Author-email: your.email@example.com
License: MIT
Classifier: Programming Language :: Python :: 3
Classifier: License :: OSI Approved :: MIT License
Classifier: Operating System :: OS Independent
License-File: LICENSE
Requires-Dist: openai
Requires-Dist: python-dotenv
Requires-Dist: click
Requires-Dist: requests
